pyMOSF/__init__.py
pyMOSF/config/__init__.py
pyMOSF/config/configs.py
pyMOSF/core/__boxed__.py
pyMOSF/core/__core__.py
pyMOSF/core/__decorators__.py
pyMOSF/core/__image_services__.py
pyMOSF/core/__init__.py
pyMOSF/core/__loggers__.py
pyMOSF/core/__safe_calls__.py
pyMOSF/core/pipelines.py
pyMOSF/kivy/__core__.py
pyMOSF/kivy/__init__.py
pyMOSF/kivy/services/__init__.py
pyMOSF/kivy/services/io.py
pyMOSF/services/__init__.py
pyMOSF/services/open_file_ios.py
pyMOSF/services/photo_picker_ios.py
pyMOSF/templates/kivy/__init__.py
pyMOSF/templates/kivy/app.py
pyMOSF/templates/kivy/example_layouts.py
pyMOSF/templates/toga/__init__.py
pyMOSF/templates/toga/__main__.py
pyMOSF/templates/toga/app.py
pyMOSF/templates/toga/example_layouts.py
pyMOSF/toga/__core__.py
pyMOSF/toga/__init__.py
pyMOSF/toga/services/__init__.py
pyMOSF/toga/services/io.py
pymosf-0.1.1.10.dist-info/licenses/LICENSE
pymosf-0.1.1.10.dist-info/METADATA
pymosf-0.1.1.10.dist-info/WHEEL
pymosf-0.1.1.10.dist-info/top_level.txt
pymosf-0.1.1.10.dist-info/RECORD
