Metadata-Version: 2.4
Name: pyMOSF
Version: 0.1.1.10
Summary: Python package for Multi-OS, Multi-Framework UI apps.
Home-page: https://github.com/rpazuki/pyMOSF
Author: Roozbeh H. Pazuki
Author-email: "Roozbeh H. Pazuki" <rpazuki@gmail.com>
License-Expression: GPL-3.0-or-later
Project-URL: Homepage, https://github.com/rpazuki/pyMOSF
Project-URL: Issues, https://github.com/rpazuki/pyMOSF/issues
Classifier: Programming Language :: Python :: 3
Classifier: Operating System :: OS Independent
Requires-Python: >=3.6
License-File: LICENSE
Requires-Dist: addict>=2.4.0
Requires-Dist: pytoml>=0.1.21
Requires-Dist: rubicon-objc>=0.4.9
Provides-Extra: dev
Requires-Dist: pytest>=6.0.0; extra == "dev"
Requires-Dist: flake8>=3.8.0; extra == "dev"
Provides-Extra: beeware
Requires-Dist: PyGObject==3.50.0; extra == "beeware"
Requires-Dist: briefcase>=0.3.22; extra == "beeware"
Requires-Dist: toga==0.4.9; extra == "beeware"
Provides-Extra: kivy
Requires-Dist: kivy>=2.3.1; extra == "kivy"
Provides-Extra: all
Requires-Dist: pytest>=6.0.0; extra == "all"
Requires-Dist: flake8>=3.8.0; extra == "all"
Requires-Dist: PyGObject==3.50.0; extra == "all"
Requires-Dist: briefcase>=0.3.22; extra == "all"
Requires-Dist: toga==0.4.9; extra == "all"
Requires-Dist: kivy>=2.3.1; extra == "all"
Provides-Extra: release
Dynamic: license-file
